gibme.py
gibme.tcss
screens/about_screen.py
screens/cheat_screen.py
screens/cve_screen.py
screens/gtfo_screen.py
screens/lol_screen.py
screens/rev_screen.py
screens/tldr_screen.py
static/data.py
gibme-0.7.15.dist-info/METADATA
gibme-0.7.15.dist-info/WHEEL
gibme-0.7.15.dist-info/entry_points.txt
gibme-0.7.15.dist-info/RECORD
