Metadata-Version: 2.1
Name: Gibme
Version: 0.7.15
Summary: A TUI tool to help make life easier for CTF and pentest
Project-URL: Homepage, https://github.com/foreztgump/gibme
Project-URL: Issues, https://github.com/foreztgump/gibme/issues
Author-email: Foreztgump <foreztgump#git@slmail.me>
Classifier: License :: OSI Approved :: MIT License
Classifier: Programming Language :: Python :: 3
Requires-Python: >=3.10
Requires-Dist: beautifulsoup4
Requires-Dist: httpx
Requires-Dist: lxml
Requires-Dist: meilisearch-python-sdk
Requires-Dist: pyexecjs
Requires-Dist: pyyaml
Requires-Dist: rapidfuzz
Requires-Dist: textual
